{
    "Id": "example-policy-1",
    "Version": "2012-10-17",
    "Statement": [
        {
            "Sid": "Enable Secrets Manager permissions to principals in account 123456789012",
            "Effect": "Allow",
            "Principal": {"AWS":["123456789012"]},
            "Action": ["secretsmanager:*"],
            "Resource": "*"
        },
        {
            "Sid": "Restrict GetSecretValue operation to only my VPC endpoint",
            "Effect": "Deny",
            "Principal": "*",
            "Action": ["secretsmanager:GetSecretValue"],
            "Resource": "*",
            "Condition": {
                "StringNotEquals": {
                    "aws:sourceVpce": "vpce-1234a5678b9012c"
                }
            }
        }

    ]
}