{
	"examples": [
		{
			"id": "cross_AuroraRestLendingLibrary",
			"file": "cross_metadata.yaml",
			"languages": {
				"Python": {
					"name": "Python",
					"property": "python",
					"versions": [
						{
							"sdk_version": 3,
							"block_content": "cross_AuroraRestLendingLibrary_Python_block.xml",
							"excerpts": [],
							"github": "python/cross_service/aurora_rest_lending_library",
							"sdkguide": null,
							"more_info": []
						}
					]
				}
			},
			"title": "Create a lending library REST API",
			"title_abbrev": "Create a lending library REST API",
			"synopsis": "create a lending library where patrons can borrow and return books by using a REST API backed by an &AURlong; database.",
			"category": "Scenarios",
			"guide_topic": null,
			"service_main": "aurora",
			"services": {
				"api-gateway": {
					"__set__": []
				},
				"aurora": {
					"__set__": []
				},
				"lambda": {
					"__set__": []
				},
				"secrets-manager": {
					"__set__": []
				}
			},
			"doc_filenames": {
				"service_pages": {
					"api-gateway": "https://docs.aws.amazon.com/code-library/latest/ug/api-gateway_example_cross_AuroraRestLendingLibrary_section.html",
					"aurora": "https://docs.aws.amazon.com/code-library/latest/ug/aurora_example_cross_AuroraRestLendingLibrary_section.html",
					"lambda": "https://docs.aws.amazon.com/code-library/latest/ug/lambda_example_cross_AuroraRestLendingLibrary_section.html",
					"secrets-manager": "https://docs.aws.amazon.com/code-library/latest/ug/secrets-manager_example_cross_AuroraRestLendingLibrary_section.html"
				},
				"sdk_pages": {
					"python": {
						"3": {
							"actions_scenarios": null,
							"cross_service": {
								"cross": "https://docs.aws.amazon.com/code-library/latest/ug/cross_AuroraRestLendingLibrary_python_3_topic.html"
							}
						}
					}
				}
			},
			"synopsis_list": [],
			"source_key": null
		},
		{
			"id": "secrets-manager_GetSecretValue",
			"file": "secrets-manager_metadata.yaml",
			"languages": {
				".NET": {
					"name": ".NET",
					"property": "csharp",
					"versions": [
						{
							"sdk_version": 3,
							"block_content": null,
							"excerpts": [
								{
									"description": null,
									"snippet_tags": [
										"SecretsManager.dotnetv3.GetSecretValueExample"
									],
									"snippet_files": [],
									"genai": "none"
								}
							],
							"github": "dotnetv3/SecretsManager",
							"sdkguide": null,
							"more_info": []
						}
					]
				},
				"Kotlin": {
					"name": "Kotlin",
					"property": "kotlin",
					"versions": [
						{
							"sdk_version": 1,
							"block_content": null,
							"excerpts": [
								{
									"description": null,
									"snippet_tags": [
										"secretsmanager.kotlin.get_secret.main"
									],
									"snippet_files": [],
									"genai": "none"
								}
							],
							"github": "kotlin/services/secrets-manager",
							"sdkguide": null,
							"more_info": []
						}
					]
				},
				"Java": {
					"name": "Java",
					"property": "java",
					"versions": [
						{
							"sdk_version": 2,
							"block_content": null,
							"excerpts": [
								{
									"description": null,
									"snippet_tags": [
										"secretsmanager.java2.get_secret.main"
									],
									"snippet_files": [],
									"genai": "none"
								}
							],
							"github": "javav2/example_code/secrets-manager",
							"sdkguide": null,
							"more_info": []
						}
					]
				},
				"Python": {
					"name": "Python",
					"property": "python",
					"versions": [
						{
							"sdk_version": 3,
							"block_content": null,
							"excerpts": [
								{
									"description": null,
									"snippet_tags": [
										"python.example_code.python.GetSecretValue.full"
									],
									"snippet_files": [],
									"genai": "none"
								}
							],
							"github": "python/example_code/secretsmanager",
							"sdkguide": null,
							"more_info": []
						}
					]
				},
				"Rust": {
					"name": "Rust",
					"property": "rust",
					"versions": [
						{
							"sdk_version": 1,
							"block_content": null,
							"excerpts": [
								{
									"description": null,
									"snippet_tags": [
										"secretsmanager.rust.get-secret-value"
									],
									"snippet_files": [],
									"genai": "none"
								}
							],
							"github": "rustv1/examples/secretsmanager",
							"sdkguide": null,
							"more_info": []
						}
					]
				},
				"C++": {
					"name": "C++",
					"property": "cpp",
					"versions": [
						{
							"sdk_version": 1,
							"block_content": null,
							"excerpts": [
								{
									"description": null,
									"snippet_tags": [
										"cpp.example_code.secrets_manager.get_secret_value"
									],
									"snippet_files": [],
									"genai": "none"
								}
							],
							"github": "cpp/example_code/secrets-manager",
							"sdkguide": null,
							"more_info": []
						}
					]
				},
				"JavaScript": {
					"name": "JavaScript",
					"property": "javascript",
					"versions": [
						{
							"sdk_version": 3,
							"block_content": null,
							"excerpts": [
								{
									"description": null,
									"snippet_tags": [
										"javascript.v3.secretsmanager.actions.GetSecretValue"
									],
									"snippet_files": [],
									"genai": "none"
								}
							],
							"github": "javascriptv3/example_code/secrets-manager",
							"sdkguide": null,
							"more_info": []
						}
					]
				}
			},
			"title": "",
			"title_abbrev": "",
			"synopsis": "",
			"category": "Api",
			"guide_topic": null,
			"service_main": null,
			"services": {
				"secrets-manager": {
					"__set__": [
						"GetSecretValue"
					]
				}
			},
			"doc_filenames": {
				"service_pages": {
					"secrets-manager": "https://docs.aws.amazon.com/code-library/latest/ug/secrets-manager_example_secrets-manager_GetSecretValue_section.html"
				},
				"sdk_pages": {
					"csharp": {
						"3": {
							"actions_scenarios": {
								"secrets-manager": "https://docs.aws.amazon.com/code-library/latest/ug/csharp_3_secrets-manager_code_examples.html#actions"
							},
							"cross_service": null
						}
					},
					"kotlin": {
						"1": {
							"actions_scenarios": {
								"secrets-manager": "https://docs.aws.amazon.com/code-library/latest/ug/kotlin_1_secrets-manager_code_examples.html#actions"
							},
							"cross_service": null
						}
					},
					"java": {
						"2": {
							"actions_scenarios": {
								"secrets-manager": "https://docs.aws.amazon.com/code-library/latest/ug/java_2_secrets-manager_code_examples.html#actions"
							},
							"cross_service": null
						}
					},
					"python": {
						"3": {
							"actions_scenarios": {
								"secrets-manager": "https://docs.aws.amazon.com/code-library/latest/ug/python_3_secrets-manager_code_examples.html#actions"
							},
							"cross_service": null
						}
					},
					"rust": {
						"1": {
							"actions_scenarios": {
								"secrets-manager": "https://docs.aws.amazon.com/code-library/latest/ug/rust_1_secrets-manager_code_examples.html#actions"
							},
							"cross_service": null
						}
					},
					"cpp": {
						"1": {
							"actions_scenarios": {
								"secrets-manager": "https://docs.aws.amazon.com/code-library/latest/ug/cpp_1_secrets-manager_code_examples.html#actions"
							},
							"cross_service": null
						}
					},
					"javascript": {
						"3": {
							"actions_scenarios": {
								"secrets-manager": "https://docs.aws.amazon.com/code-library/latest/ug/javascript_3_secrets-manager_code_examples.html#actions"
							},
							"cross_service": null
						}
					}
				}
			},
			"synopsis_list": [],
			"source_key": null
		},
		{
			"id": "secrets-manager_BatchGetSecretValue",
			"file": "secrets-manager_metadata.yaml",
			"languages": {
				"Python": {
					"name": "Python",
					"property": "python",
					"versions": [
						{
							"sdk_version": 3,
							"block_content": null,
							"excerpts": [
								{
									"description": null,
									"snippet_tags": [
										"python.example_code.python.BatchGetSecretValue.full"
									],
									"snippet_files": [],
									"genai": "none"
								}
							],
							"github": "python/example_code/secretsmanager",
							"sdkguide": null,
							"more_info": []
						}
					]
				}
			},
			"title": "",
			"title_abbrev": "",
			"synopsis": "",
			"category": "Api",
			"guide_topic": null,
			"service_main": null,
			"services": {
				"secrets-manager": {
					"__set__": [
						"BatchGetSecretValue"
					]
				}
			},
			"doc_filenames": {
				"service_pages": {
					"secrets-manager": "https://docs.aws.amazon.com/code-library/latest/ug/secrets-manager_example_secrets-manager_BatchGetSecretValue_section.html"
				},
				"sdk_pages": {
					"python": {
						"3": {
							"actions_scenarios": {
								"secrets-manager": "https://docs.aws.amazon.com/code-library/latest/ug/python_3_secrets-manager_code_examples.html#actions"
							},
							"cross_service": null
						}
					}
				}
			},
			"synopsis_list": [],
			"source_key": null
		}
	]
}